Metadata-Version: 2.1
Name: dalymi
Version: 0.1.5
Summary: [data like you mean it] A lightweight, data-focused and non-opinionated pipeline manager written in and for Python.
Home-page: https://github.com/joschnitzbauer/dalymi
Author: Joerg Schnitzbauer
Author-email: joschnitzbauer@gmail.com
License: MIT
Platform: UNKNOWN
